ml_utils/__init__.py
ml_utils/analysis/Overview.py
ml_utils/analysis/Plot.py
ml_utils/analysis/__init__.py
ts_utils/__init__.py
smartpyml-0.1.2.dist-info/LICENSE
smartpyml-0.1.2.dist-info/METADATA
smartpyml-0.1.2.dist-info/WHEEL
smartpyml-0.1.2.dist-info/top_level.txt
smartpyml-0.1.2.dist-info/RECORD
