Metadata-Version: 2.1
Name: smartpyml
Version: 0.1.2
Summary: smartpyml: A Comprehensive Machine Learning Library
Home-page: https://github.com/srikresna/smartpyml
Author: srikresna
Author-email: srikresna383@gmail.com
Keywords: machine learning,data science,automl,ai
Classifier: Development Status :: 3 - Alpha
Classifier: Intended Audience :: Developers
Classifier: License :: OSI Approved :: MIT License
Classifier: Programming Language :: Python :: 3
Classifier: Programming Language :: Python :: 3.6
Classifier: Programming Language :: Python :: 3.7
Classifier: Programming Language :: Python :: 3.8
License-File: LICENSE
Requires-Dist: numpy
Requires-Dist: pandas
Requires-Dist: xlrd
Requires-Dist: matplotlib
Requires-Dist: seaborn
Requires-Dist: scipy
Requires-Dist: statsmodels
Requires-Dist: scikit-learn
Requires-Dist: imbalanced-learn
Requires-Dist: ppscore
Requires-Dist: tensorflow
Requires-Dist: minisom
Requires-Dist: lime
Requires-Dist: shap
Requires-Dist: geopy
Requires-Dist: folium
